konect2networkx/Loader.py
konect2networkx/Parser.py
konect2networkx/__init__.py
konect2networkx/exceptions.py
konect2networkx/main.py
konect2networkx-0.1.1.dist-info/LICENSE
konect2networkx-0.1.1.dist-info/METADATA
konect2networkx-0.1.1.dist-info/WHEEL
konect2networkx-0.1.1.dist-info/top_level.txt
konect2networkx-0.1.1.dist-info/RECORD
