Metadata-Version: 2.1
Name: konect2networkx
Version: 0.1.1
Summary: Python package bridging the gap between the KONECT project and NetworkX
Home-page: https://github.com/jkudla/konect2networkx
Author: Jannik Kudla
Author-email: jannik.kudla@maths.ox.ac.uk
License: GPLv3
Platform: UNKNOWN
Classifier: Intended Audience :: Developers
Classifier: License :: OSI Approved :: GNU General Public License v3 (GPLv3)
Classifier: Programming Language :: Python
Classifier: Programming Language :: Python :: 3
Classifier: Operating System :: OS Independent
Requires-Dist: requests
Requires-Dist: networkx
